bibchk/__init__.py
bibchk/bibtex.py
bibchk/cli.py
bibchk/document.py
bibchk/doi.py
bibchk/isbn.py
bibchk-0.2.0.dist-info/LICENSE
bibchk-0.2.0.dist-info/METADATA
bibchk-0.2.0.dist-info/WHEEL
bibchk-0.2.0.dist-info/entry_points.txt
bibchk-0.2.0.dist-info/top_level.txt
bibchk-0.2.0.dist-info/RECORD
