Metadata-Version: 2.1
Name: bibchk
Version: 0.2.0
Summary: Simple command line program to return the BibTeX string of a given DOI or ISBN.
Home-page: https://github.com/BibTheque/bibchk
Author: Doug Keller
Author-email: dg.kllr.jr@gmail.com
Classifier: Programming Language :: Python :: 3
Classifier: License :: OSI Approved :: GNU Lesser General Public License v2 or later (LGPLv2+)
Classifier: Operating System :: OS Independent
Requires-Python: >=3.9
License-File: LICENSE
Requires-Dist: click
Requires-Dist: bibtexparser
Requires-Dist: habanero
Requires-Dist: isbnlib
